google/api/annotations_pb2.py
google/api/annotations_pb2_grpc.py
google/api/auth_pb2.py
google/api/auth_pb2_grpc.py
google/api/backend_pb2.py
google/api/backend_pb2_grpc.py
google/api/billing_pb2.py
google/api/billing_pb2_grpc.py
google/api/client_pb2.py
google/api/client_pb2_grpc.py
google/api/config_change_pb2.py
google/api/config_change_pb2_grpc.py
google/api/consumer_pb2.py
google/api/consumer_pb2_grpc.py
google/api/context_pb2.py
google/api/context_pb2_grpc.py
google/api/control_pb2.py
google/api/control_pb2_grpc.py
google/api/distribution_pb2.py
google/api/distribution_pb2_grpc.py
google/api/documentation_pb2.py
google/api/documentation_pb2_grpc.py
google/api/endpoint_pb2.py
google/api/endpoint_pb2_grpc.py
google/api/error_reason_pb2.py
google/api/error_reason_pb2_grpc.py
google/api/field_behavior_pb2.py
google/api/field_behavior_pb2_grpc.py
google/api/field_info_pb2.py
google/api/field_info_pb2_grpc.py
google/api/http_pb2.py
google/api/http_pb2_grpc.py
google/api/httpbody_pb2.py
google/api/httpbody_pb2_grpc.py
google/api/label_pb2.py
google/api/label_pb2_grpc.py
google/api/launch_stage_pb2.py
google/api/launch_stage_pb2_grpc.py
google/api/log_pb2.py
google/api/log_pb2_grpc.py
google/api/logging_pb2.py
google/api/logging_pb2_grpc.py
google/api/metric_pb2.py
google/api/metric_pb2_grpc.py
google/api/monitored_resource_pb2.py
google/api/monitored_resource_pb2_grpc.py
google/api/monitoring_pb2.py
google/api/monitoring_pb2_grpc.py
google/api/policy_pb2.py
google/api/policy_pb2_grpc.py
google/api/quota_pb2.py
google/api/quota_pb2_grpc.py
google/api/resource_pb2.py
google/api/resource_pb2_grpc.py
google/api/routing_pb2.py
google/api/routing_pb2_grpc.py
google/api/service_pb2.py
google/api/service_pb2_grpc.py
google/api/source_info_pb2.py
google/api/source_info_pb2_grpc.py
google/api/system_parameter_pb2.py
google/api/system_parameter_pb2_grpc.py
google/api/usage_pb2.py
google/api/usage_pb2_grpc.py
google/api/visibility_pb2.py
google/api/visibility_pb2_grpc.py
yandex_speechkit-1.5.0.dist-info/METADATA
yandex_speechkit-1.5.0.dist-info/WHEEL
yandex_speechkit-1.5.0.dist-info/top_level.txt
yandex_speechkit-1.5.0.dist-info/RECORD
