Metadata-Version: 2.1
Name: yandex-speechkit
Version: 1.5.0
Summary: SpeechKit package
Home-page: UNKNOWN
Author: eranik
Author-email: eranik@yandex-team.ru
License: apache-2.0
Keywords: speechkit
Platform: UNKNOWN
Requires-Python: >=3.7
Requires-Dist: grpcio
Requires-Dist: protobuf
Requires-Dist: pydub
Requires-Dist: requests
